[{"id":"238cc220dc472f9122764a7a7cd2dea968c0bf076d4f1fb5121bf8bb6a4dde6e","name":"栗東なす耳鼻咽喉科","prefId":25,"mdepart1":"耳鼻咽喉科","mdepart2":"アレルギー科","mdepart3":null,"address1":"滋賀県栗東市","address2":"下鈎864-1","tel":"0775548714","url":"http://www.ritto-nasu.com/","firstvisit":true,"rediagnosis":true,"covid19":false,"otherinfo":"https://clinics.medley.life/clinics/59b1f11f0ac54c0087679232"},{"id":"8a92793c17fde7464dadcfe03ba28888212b4553675f5d0b53b066fab4ba01f7","name":"布留クリニック","prefId":25,"mdepart1":"リウマチ科","mdepart2":"内科","mdepart3":"整形外科","address1":"滋賀県甲賀市","address2":"甲南町寺庄","tel":null,"url":"http://www.furu-clinic.jp","firstvisit":false,"rediagnosis":false,"covid19":false,"otherinfo":null},{"id":"3ec0620c8e66ed6427f6df36101b035697ee99ed7c42a567a0924d59973844ea","name":"うちだクリニック","prefId":25,"mdepart1":"内科","mdepart2":"循環器科","mdepart3":"呼吸器科","address1":"滋賀県守山市","address2":"守山5-8-7","tel":"0775143633","url":"http://www.uchida-c.com/","firstvisit":false,"rediagnosis":true,"covid19":false,"otherinfo":"https://clinics.medley.life/clinics/59cdb6823dc9170088a0e827"},{"id":"2aee4f78545165f0390686e6f85fbdd412dd8a655882950dd5a94da7da2d9048","name":"津田内科医院","prefId":25,"mdepart1":"内科","mdepart2":"呼吸器内科","mdepart3":null,"address1":"滋賀県守山市","address2":"焔魔堂町15","tel":"0775823094","url":"http://www.tsudanaika.com/","firstvisit":false,"rediagnosis":true,"covid19":false,"otherinfo":"https://clinics.medley.life/clinics/5ab4bdc1174707297e32fdbf"},{"id":"9e855a852c93fae0386318393b50cf5540c1878797221cb4d45b2a2e7570802d","name":"医療法人いしべ耳鼻咽喉科","prefId":25,"mdepart1":"耳鼻咽喉科","mdepart2":null,"mdepart3":null,"address1":"滋賀県守山市","address2":"吉身２丁目6-51","tel":null,"url":"https://www.e33.jp","firstvisit":false,"rediagnosis":true,"covid19":false,"otherinfo":null},{"id":"186f292903ee3760be612b9ac3f7dddfa7bb4d3becde48aa865c104b01f317f7","name":"ひろたに医院","prefId":25,"mdepart1":"内科","mdepart2":"糖尿病","mdepart3":"循環器内科","address1":"滋賀県守山市","address2":"大林町214-5","tel":"077-581-3636","url":"https://www.hirotaiin.com/index.html","firstvisit":false,"rediagnosis":true,"covid19":false,"otherinfo":null},{"id":"912cb44a3120ba2ff96283c87bd85556790eb0d8df68307e4f71d22c29b14a2e","name":"医療法人社団ラナンキュラス会 麗ビューティー皮フ科クリニック","prefId":25,"mdepart1":"皮膚科","mdepart2":"美容皮膚科","mdepart3":"形成外科","address1":"滋賀県草津市","address2":"西大路町4-32 クサツエストピアホテル1F","tel":"0775695509","url":"https://www.rei-beauty.com/","firstvisit":false,"rediagnosis":true,"covid19":false,"otherinfo":"https://clinics.medley.life/clinics/5d7b4aad5e21325b37ccf44d"},{"id":"9d12383146729d55bd4254193c8a9ca3afb805a4e1d55ba33d1c8662eb013afc","name":"医療法人大美会 大西皮フ科形成外科医院","prefId":25,"mdepart1":"皮膚科","mdepart2":"美容皮膚科","mdepart3":"形成外科","address1":"滋賀県大津市","address2":"栗津町4-7 JR石山駅前近江鉄道ビル3F","tel":"0775312101","url":"http://www.onishiskinclinic.com/index.html","firstvisit":false,"rediagnosis":false,"covid19":false,"otherinfo":"https://clinics.medley.life/clinics/5ae0099f4168781d5f89c459"},{"id":"7a256348a1848ff33569a9f2082caa273816ed08ba960981989cdb6eaee09963","name":"青地うえだクリニック","prefId":25,"mdepart1":"産婦人科","mdepart2":"婦人科","mdepart3":null,"address1":"滋賀県大津市","address2":"中央1-1-6","tel":"0775223940","url":"http://www.aoueda-cl.com/index.html","firstvisit":false,"rediagnosis":true,"covid19":false,"otherinfo":"https://clinics.medley.life/clinics/5b56f24a881528602ea2bf8c"},{"id":"460f8b91cfe26e6c010fce1b4243f0d8839d7ed9edca6afd8c5b676549d3649b","name":"医療法人 はしもと歯科医院","prefId":25,"mdepart1":"歯科","mdepart2":"歯科口腔外科","mdepart3":"矯正歯科","address1":"滋賀県大津市","address2":"本堅田4-18-38","tel":"0775745551","url":"https://www.hashimotosika.jp","firstvisit":false,"rediagnosis":false,"covid19":false,"otherinfo":"https://clinics.medley.life/clinics/5c5250eff53d1737540bfb6d"},{"id":"de24a4a8f261d45f5171facf03c8556c4851c384d30f5b29f5f6f1c97feb205a","name":"ばんば耳鼻咽喉科医院","prefId":25,"mdepart1":"耳鼻咽喉科","mdepart2":null,"mdepart3":null,"address1":"滋賀県大津市","address2":"見世2丁目19-50","tel":null,"url":"http://bamba-ent.com/","firstvisit":false,"rediagnosis":false,"covid19":false,"otherinfo":null},{"id":"0b2cfbf90c9b03ef8e99fed3ff81fc129eee2a511d26a119420d69bb62336d5b","name":"医療法人遙山会 南彦根クリニック","prefId":25,"mdepart1":"精神科","mdepart2":"心療内科","mdepart3":null,"address1":"滋賀県彦根市","address2":"西今町138","tel":"0749247808","url":"https://www.biwako.ne.jp/~mihikocl/","firstvisit":false,"rediagnosis":true,"covid19":false,"otherinfo":"https://clinics.medley.life/clinics/5bfcac402dd8ab423664a6c5"},{"id":"9e634c04fed0c8f049638925b24d0b49a8091079d05b115fe5008e4db4af1037","name":"なかつか内科医院","prefId":25,"mdepart1":"内科","mdepart2":"呼吸内科","mdepart3":"循環器内科","address1":"滋賀県彦根市","address2":"川瀬馬場町1082番地5彦根クリニックモール内科棟","tel":null,"url":"http://www.eonet.ne.jp/~nakatsuka-c/","firstvisit":false,"rediagnosis":true,"covid19":false,"otherinfo":null},{"id":"438bdcdcb8b4efa1db284f9a84421310e014d0b56ab3227555187b2e9c2f9bf2","name":"藤岡内科医院","prefId":"25","mdepart1":"内科","mdepart2":"","mdepart3":"","address1":"滋賀県大津市黒津２−２−３","address2":"","tel":"077-536-3522","url":"http://www.fujioka-naika.jp","firstvisit":false,"rediagnosis":false,"covid19":"-","doctors":"藤岡秀行","otherinfo":"-"},{"id":"fca8e3f02d4562071671ca9b52a1ecadc40ed9a6bb9803a1b081af04698ddff4","name":"医療法人赫照会ひらた医院","prefId":"25","mdepart1":"内科循環器内科","mdepart2":"","mdepart3":"","address1":"滋賀県大津市石山寺3-15-10","address2":"","tel":"077-537-5537","url":null,"firstvisit":true,"rediagnosis":true,"covid19":"-","doctors":"平田和人","otherinfo":"-"},{"id":"167fb23883ccc9b7dfd48c868bfaa6482bd6bf2c84d03c77da03fc34d7e392e8","name":"膳所診療所","prefId":"25","mdepart1":"内科小児科","mdepart2":"","mdepart3":"","address1":"滋賀県大津市昭和町2-17","address2":"","tel":"077-524-8114","url":null,"firstvisit":false,"rediagnosis":true,"covid19":"-","doctors":"東昌子鉄谷新平","otherinfo":"-"},{"id":"6fc873dd68f5226187eac207434d1423d5f668aa1af9caff313156ef028a6dca","name":"竹内医院","prefId":"25","mdepart1":"内科小児科","mdepart2":"","mdepart3":"","address1":"滋賀県大津市横木1-8-10","address2":"","tel":"077-522-4319","url":null,"firstvisit":true,"rediagnosis":true,"covid19":"-","doctors":"清河滋子","otherinfo":"-"},{"id":"34fd5707eadbffe488512787249dd32f6207132c3410a378bbb316617257daea","name":"瀬田しもぞの眼科","prefId":"25","mdepart1":"眼科","mdepart2":"","mdepart3":"","address1":"滋賀県大津市大将軍3丁目24番6号","address2":"","tel":"077-545-8000","url":"http://www.shimozonoganka.com","firstvisit":true,"rediagnosis":true,"covid19":"-","doctors":"下園正剛","otherinfo":"-"},{"id":"19ee956d3cd44034c93154cc36a03fbf24e48f64a41c0ca9191c2f91637c67ea","name":"医療法人銀杏会まつだ内科胃腸科","prefId":"25","mdepart1":"内科胃腸科","mdepart2":"","mdepart3":"","address1":"滋賀県大津市雄琴北1丁目6-14","address2":"","tel":"077-577-3210","url":"web.kyoto-inet.or.jp/peopie/matsu35/","firstvisit":true,"rediagnosis":true,"covid19":"-","doctors":"松田博","otherinfo":"-"},{"id":"e1e2a85d70f197c9c58feb3bbbe60bf35a879aeec43bb05ebe63fd64b8bb2a7b","name":"ふくた診療所","prefId":"25","mdepart1":"内科","mdepart2":"","mdepart3":"","address1":"滋賀県大津市八屋戸971-5","address2":"","tel":"077-592-8003","url":null,"firstvisit":true,"rediagnosis":true,"covid19":"-","doctors":"福田章典","otherinfo":"-"},{"id":"6b7a77b861424d0fa62f17be118ae87fde9609cddb3af7dec4101810ed23ad3c","name":"なかじま内科クリニック","prefId":"25","mdepart1":"内科消化器内科","mdepart2":"","mdepart3":"","address1":"滋賀県大津市浜大津2丁目1-32-1","address2":"","tel":"077-536-5181","url":null,"firstvisit":false,"rediagnosis":true,"covid19":"-","doctors":"中島年和","otherinfo":"-"},{"id":"1be05ec72108d3f9ec60a68e804ab24e3de580f54f4e93271d3ab1b04af6e342","name":"いしやま内科整形外科","prefId":"25","mdepart1":"内科呼吸器科","mdepart2":"","mdepart3":"","address1":"滋賀県大津市松原町14-7","address2":"","tel":"077-574-7700","url":"http://ishiyama-naika-seikei.com","firstvisit":true,"rediagnosis":true,"covid19":"-","doctors":"奥村喜章森川淳一郎高橋奥田薫大塚武人大野将司山口小川仲川山崎澤山裕一肥後","otherinfo":"-"},{"id":"43c0e0dbfa7d6aa728d5ced960f5d300498467221fc865cbd99fdb4b6078ad77","name":"矢沢耳鼻咽喉科医院","prefId":"25","mdepart1":"耳鼻科","mdepart2":"","mdepart3":"","address1":"滋賀県大津市大江3-24-15","address2":"","tel":"077-544-3110","url":"http://www7a.biglobe.ne.jp/~yazawa-ent","firstvisit":true,"rediagnosis":true,"covid19":"-","doctors":"矢沢代四郎","otherinfo":"-"},{"id":"3b8f322a8f6cbe2d355d635d9617593d7b88f6d8acd16336ebf3619effb96db2","name":"高槻医院","prefId":"25","mdepart1":"内科小児科","mdepart2":"","mdepart3":"","address1":"滋賀県大津市松本2-4-37","address2":"","tel":"077-522-3991","url":null,"firstvisit":true,"rediagnosis":true,"covid19":"-","doctors":"高槻義夫高槻信夫","otherinfo":"-"},{"id":"b8d3bfcb9ea3bb490dc1ec477a4ef3e377bbcd2cf68397589419fede6270a0f8","name":"大西クリニック","prefId":"25","mdepart1":"内科小児科","mdepart2":"","mdepart3":"","address1":"滋賀県大津市浜大津3丁目7番23号","address2":"","tel":"077-523-5911","url":null,"firstvisit":true,"rediagnosis":true,"covid19":"-","doctors":"大西利穂","otherinfo":"-"},{"id":"d666e1677dddef50c29a90444c2ea2775684a4e4ab578a57d2a5dd0e5a8ab3a1","name":"西大津耳鼻咽喉科","prefId":"25","mdepart1":"耳鼻咽喉科","mdepart2":"","mdepart3":"","address1":"滋賀県大津市皇子が丘2-10-25-104","address2":"","tel":"077-510-5454","url":"http://www.nishiotsu-ent.com","firstvisit":true,"rediagnosis":true,"covid19":"-","doctors":"増田信弘","otherinfo":"-"},{"id":"b1d33540c208fcd217d362224470a9c3be61d761683c03ef654a282d41ab7552","name":"岡本医院","prefId":"25","mdepart1":"内科小児科","mdepart2":"","mdepart3":"","address1":"滋賀県大津市本堅田1丁目18-21","address2":"","tel":"077-573-2838","url":"https://okamoto-cl.jp","firstvisit":true,"rediagnosis":true,"covid19":"-","doctors":"岡本芳郎岡本宣浩","otherinfo":"-"},{"id":"fe172facf45dd7b84cee3355745f51b1d23d0b45f992c377a6cf78cad6fcfecc","name":"医療法人高山内科循環器科","prefId":"25","mdepart1":"内科","mdepart2":"","mdepart3":"","address1":"滋賀県彦根市日夏町２６８０−３５","address2":"","tel":"0749-28-7007","url":null,"firstvisit":true,"rediagnosis":true,"covid19":"-","doctors":"高山幸男","otherinfo":"-"},{"id":"b01c8256038938e801d3edbb9333a9aab1cbb59536b3f09e8b1680b497a16e2d","name":"藤野こどもクリニック","prefId":"25","mdepart1":"小児科","mdepart2":"","mdepart3":"","address1":"滋賀県彦根市戸賀町３６−６","address2":"","tel":"0749-47-5311","url":"http://www.fujino-kodomo.jp","firstvisit":true,"rediagnosis":true,"covid19":"-","doctors":"藤野英俊","otherinfo":"-"},{"id":"eace78a50ab7e84250435a4aca5824ea3d713c499b86d7eeab7aafe607542af6","name":"石川耳鼻咽喉科","prefId":"25","mdepart1":"耳鼻咽喉科","mdepart2":"","mdepart3":"","address1":"滋賀県彦根市中薮町727-8","address2":"","tel":"0749-24-4187","url":null,"firstvisit":false,"rediagnosis":true,"covid19":"-","doctors":"石川保之","otherinfo":"-"},{"id":"369eb9edab61bfd6962a753568ddb2e12cc1315a545d906dbc7704f253630095","name":"松木診療所","prefId":"25","mdepart1":"内科","mdepart2":"","mdepart3":"","address1":"滋賀県彦根市平田町678-10","address2":"","tel":"0749-22-5185","url":null,"firstvisit":false,"rediagnosis":true,"covid19":"-","doctors":"松木","otherinfo":"-"},{"id":"0353c0cb5b96385e36e21be44a808a1e28c9039ca27d4f7c026a6447ca2663d1","name":"辰巳医院","prefId":"25","mdepart1":"内科小児科","mdepart2":"","mdepart3":"","address1":"滋賀県彦根市西沼波町269-18","address2":"","tel":"0749-22-1180","url":null,"firstvisit":false,"rediagnosis":true,"covid19":"-","doctors":"辰巳裕之","otherinfo":"-"},{"id":"7a35f734e1bddebd24f0f69eaf46ddcc0864fc516e3fe673df8b9c0857d8d4a0","name":"いけだ内科医院","prefId":"25","mdepart1":"内科","mdepart2":"","mdepart3":"","address1":"滋賀県彦根市野瀬町18-8","address2":"","tel":"0749-21-6060","url":null,"firstvisit":false,"rediagnosis":true,"covid19":"-","doctors":"池田智之","otherinfo":"-"},{"id":"60a0d012a33a4ef6a033e5adff7dfdf49e0cb9fc54855b5e7d97401aff23298c","name":"医療法人坂田整形外科","prefId":"25","mdepart1":"整形外科","mdepart2":"","mdepart3":"","address1":"滋賀県彦根市清崎町288-37","address2":"","tel":"0749-28-3737","url":null,"firstvisit":true,"rediagnosis":true,"covid19":"-","doctors":"坂田勝朗","otherinfo":"-"},{"id":"10af14349884404c1de4b2de4a6c44eb5c0ce1620439bd3b3bcf32f90740482a","name":"なかつか内科医院","prefId":"25","mdepart1":"内科","mdepart2":"","mdepart3":"","address1":"滋賀県彦根市川瀬馬場町1082番地5","address2":"","tel":"0749-29-0981","url":"http://www.eonet.ne.jp/nakatsuka-c/","firstvisit":true,"rediagnosis":true,"covid19":"-","doctors":"中塚貴之","otherinfo":"-"},{"id":"87c4edcd9fa201134f8ebf6d2108d9fe1fd855b543c91595bb5b5501747022f2","name":"風の街こどもクリニック","prefId":"25","mdepart1":"小児科","mdepart2":"","mdepart3":"","address1":"滋賀県長浜市八幡中山町３６１","address2":"","tel":"0749-68-2100","url":"http://www.kazenomachi-kodomo.website/","firstvisit":false,"rediagnosis":false,"covid19":"-","doctors":"山根達也","otherinfo":"-"},{"id":"6f1a9e97847100707d23eab429762dd95e33387e9234fe21c514457edfc0cc5c","name":"にしあざい診療所","prefId":"25","mdepart1":"内科小児科","mdepart2":"","mdepart3":"","address1":"滋賀県長浜市西浅井町大浦2590番地","address2":"","tel":"0749-89-0012","url":"https://nishiazai,jadecom.or.jp","firstvisit":false,"rediagnosis":true,"covid19":"-","doctors":"上田祐樹木村佳弘","otherinfo":"-"},{"id":"4af09bae0906c939456b6c11777a0624b284a61bfc3fc6dec625f97f2392e1e0","name":"塩津出張診療所","prefId":"25","mdepart1":"内科小児科","mdepart2":"","mdepart3":"","address1":"滋賀県長浜市西浅井町塩津浜1795番地","address2":"","tel":"0749-88-0341","url":null,"firstvisit":false,"rediagnosis":true,"covid19":"-","doctors":"木村佳弘","otherinfo":"-"},{"id":"7178d6b833e5f1a19c96b1cb68d583f641750a35715e55e818138672f7a43246","name":"菅浦出張診療所","prefId":"25","mdepart1":"内科小児科","mdepart2":"","mdepart3":"","address1":"滋賀県長浜市西浅井町菅浦218番地","address2":"","tel":"0749-89-0506","url":null,"firstvisit":false,"rediagnosis":true,"covid19":"-","doctors":"上田祐樹","otherinfo":"-"},{"id":"7ae49dcea12581a3f411aa5e7dfc0461b28e595bfd080b450e901327cd47556b","name":"岩本整形外科","prefId":"25","mdepart1":"整形外科","mdepart2":"","mdepart3":"","address1":"滋賀県長浜市大戌亥町738番地-4号","address2":"","tel":"0749-64-1866","url":null,"firstvisit":true,"rediagnosis":true,"covid19":"-","doctors":"岩本貴志","otherinfo":"-"},{"id":"cc98da1877871d42f09511f5ce98d973651ce24259a7996fcbb0acdebe4e82bc","name":"アップルクリニック","prefId":"25","mdepart1":"心療内科","mdepart2":"","mdepart3":"","address1":"滋賀県長浜市南呉服町9-2中村屋ビル2F","address2":"","tel":"0749-68-0355","url":"http://apple-clinic.jp","firstvisit":true,"rediagnosis":true,"covid19":"-","doctors":"速水正博","otherinfo":"-"},{"id":"76870c66ca4bec58a39444ee4a43c74035fa5228e12c5a661f09fe4ecc62894a","name":"伊良子医院","prefId":"25","mdepart1":"内科","mdepart2":"","mdepart3":"","address1":"滋賀県近江八幡市十王町１２３","address2":"","tel":"0748-36-8012","url":null,"firstvisit":true,"rediagnosis":true,"covid19":"-","doctors":"山雄久美山雄健次赤松園子","otherinfo":"-"},{"id":"ee8111d26d5598e1db9c820dc336490cf15cef80e4d85bb7f3de32537bf591e0","name":"おうみリウマチ膠原病・内科クリニック","prefId":"25","mdepart1":"内科リウマチ科アレルギー科","mdepart2":"","mdepart3":"","address1":"滋賀県近江八幡市中村町20-25","address2":"","tel":"0748-31-1888","url":"http://www.oumi-rc.com","firstvisit":false,"rediagnosis":true,"covid19":"-","doctors":"川端大介","otherinfo":"-"},{"id":"4cdcda0892527305f68222a313367616bc274a5a7f094585e1fa016b4fca8b35","name":"まつだクリニック","prefId":"25","mdepart1":"外科整形外科内科","mdepart2":"","mdepart3":"","address1":"滋賀県近江八幡市桜宮町211番地3","address2":"","tel":"0748-33-2703","url":"www.ok-health.jp/about/","firstvisit":false,"rediagnosis":true,"covid19":"-","doctors":"松田孝一山本昇","otherinfo":"-"},{"id":"39c129ac82f5ddf755a113f3e59c0bb669c3522765e99e4708e048cef52307ce","name":"医療法人社団柴田医院","prefId":"25","mdepart1":"内科消化器科","mdepart2":"","mdepart3":"","address1":"滋賀県近江八幡市鷹飼町北1-8-6","address2":"","tel":"0748-31-3637","url":null,"firstvisit":false,"rediagnosis":true,"covid19":"-","doctors":"柴田辰己","otherinfo":"-"},{"id":"52b3876be6c07f0625e0920eff8f3a8a29168a8019739e5be465ac5d4f4eec4c","name":"医療法人宮腰内科医院","prefId":"25","mdepart1":"内科","mdepart2":"","mdepart3":"","address1":"滋賀県近江八幡市白鳥町26-1","address2":"","tel":"0748-32-0028","url":"https://www.miyakoshi-naikaiin.com","firstvisit":false,"rediagnosis":true,"covid19":"-","doctors":"宮腰正信宮腰大輔","otherinfo":"-"},{"id":"52d25421c85296cb3f0db385e388d87ae6111ffe95c470267f03ebcf284d4aaa","name":"浅野医院","prefId":"25","mdepart1":"内科","mdepart2":"","mdepart3":"","address1":"滋賀県近江八幡市千僧供町265番地","address2":"","tel":"0748-37-0246","url":null,"firstvisit":false,"rediagnosis":true,"covid19":"-","doctors":"浅野定弘","otherinfo":"-"},{"id":"cbdc43770615a351aff05c6fa69f0cab59b22fe6aa6b9a0e74a95d6d521cd7d3","name":"白鳥医院","prefId":"25","mdepart1":"内科脳神経内科","mdepart2":"","mdepart3":"","address1":"滋賀県近江八幡市鷹飼町450-5","address2":"","tel":"0748-43-1178","url":"https://shiratoriclinic.com","firstvisit":true,"rediagnosis":true,"covid19":"-","doctors":"田原美喜","otherinfo":"-"},{"id":"1b3b1a3f44fd39fc0b3b013db1fae74b7c08b00222e365db378f09acce60466d","name":"近江草津徳洲会病院","prefId":"25","mdepart1":"規定なし","mdepart2":"","mdepart3":"","address1":"滋賀県草津市東矢倉3-34-52","address2":"","tel":"077-567-3610","url":"https://www.oumi-kusatsu-hp.jp","firstvisit":true,"rediagnosis":true,"covid19":"-","doctors":"外来診療担当表に基づく","otherinfo":"-"},{"id":"bd545cafd2db7b040c1d318549f382a354ec4dfe177b4a5f015043a9f42ed5c0","name":"北山田診療所","prefId":"25","mdepart1":"内科小児科","mdepart2":"","mdepart3":"","address1":"滋賀県草津市北山田町245-1","address2":"","tel":"077-566-2560077-567-4611","url":null,"firstvisit":true,"rediagnosis":true,"covid19":"-","doctors":"馬場史道馬場典子","otherinfo":"-"},{"id":"209bdd8016d4bbe22a497576bf3f0e8046129226031e4d970a99c47d97e53b14","name":"いづ井上内科","prefId":"25","mdepart1":"内科消化器循環器呼吸器","mdepart2":"","mdepart3":"","address1":"滋賀県草津市青地町481-3","address2":"","tel":"077-567-8502","url":"http://www.eonet.ne.jp/~kowloon/","firstvisit":false,"rediagnosis":true,"covid19":"-","doctors":"井上佐知子井上慎二","otherinfo":"-"},{"id":"91e53bfad357a41d8e4e6de3fb160e16a429a783ccee1acb8f9a575da5cef817","name":"そうむらこどもクリニック","prefId":"25","mdepart1":"小児科","mdepart2":"","mdepart3":"","address1":"滋賀県草津市追分南4-6-23","address2":"","tel":"077-548-6655","url":"http://soumura-cl.com","firstvisit":true,"rediagnosis":true,"covid19":"-","doctors":"宗村純平","otherinfo":"-"},{"id":"51f3fd6a40938f7c77c3d09f487e98d56c899244b79b0ca0c0dc9a3a3ef29c4c","name":"伊藤内科クリニック","prefId":"25","mdepart1":"循環器内科、内科","mdepart2":"","mdepart3":"","address1":"滋賀県草津市西大路町4番32-106号1","address2":"","tel":"077-563-3550","url":"http://ito-med.com/","firstvisit":false,"rediagnosis":true,"covid19":"-","doctors":"伊藤誠","otherinfo":"-"},{"id":"527e07da3e8bad386874db2381b501d1ba43e9bbe7e1d1d68c9f20b7842fa8ff","name":"おがわ耳鼻咽喉科医院","prefId":"25","mdepart1":"耳鼻科","mdepart2":"","mdepart3":"","address1":"滋賀県草津市追分1丁目4番地25-2","address2":"","tel":"077-516-8733","url":"https://ssc3.doctorqube.com/ogawa-jibika/","firstvisit":true,"rediagnosis":true,"covid19":"-","doctors":"小河孝夫","otherinfo":"-"},{"id":"869f51c314c6dc7d165858e3a2eacc871d422836d1c692150b46f3417dd3ee0f","name":"南草津病院","prefId":"25","mdepart1":"内科整形外科外科神経内科","mdepart2":"","mdepart3":"","address1":"滋賀県草津市野路5丁目２−３９","address2":"","tel":"077-562-0724","url":"https://373932hp.jp/","firstvisit":false,"rediagnosis":true,"covid19":"-","doctors":"遠藤程原田村李喜多内藤船越吉藤内藤宮本松井矢端金子小橋小川金荒木原","otherinfo":"-"},{"id":"1b376198da772d3fbbac5e765874e21a373509caa38f51c767a26f119e28f71a","name":"内科胃腸科井上クリニック","prefId":"25","mdepart1":"内科胃腸科","mdepart2":"","mdepart3":"","address1":"滋賀県守山市吉身3丁目14-46","address2":"","tel":"077-581-1233","url":null,"firstvisit":true,"rediagnosis":true,"covid19":"-","doctors":"井上久行","otherinfo":"-"},{"id":"415d956853c6e8ca3feb0fd0385a1d09002ca39955bdd9c18b209ae1f4181591","name":"いしべ耳鼻咽喉科","prefId":"25","mdepart1":"耳鼻咽喉科アレルギー科小児科","mdepart2":"","mdepart3":"","address1":"滋賀県守山市吉身2丁目6-51","address2":"","tel":"077-582-1334","url":"www.e33.jp","firstvisit":true,"rediagnosis":true,"covid19":"-","doctors":"石部司","otherinfo":"-"},{"id":"752d66d244c8fe2f24eee715440e621635f97b5127a410b8652801203295b6a7","name":"医療法人かさはら医院","prefId":"25","mdepart1":"内科整形外科外科神経内科","mdepart2":"","mdepart3":"","address1":"滋賀県守山市播磨田町1456-1","address2":"","tel":"077-514-0003","url":null,"firstvisit":true,"rediagnosis":true,"covid19":"-","doctors":"笠原崇笠原吉孝今井雄太関根理","otherinfo":"-"},{"id":"305fcb7bbe647648add02935bfddcafd534cab5b321953f6bddfadb7189126b9","name":"ひろたに医院","prefId":"25","mdepart1":"内科小児科(6歳以上)","mdepart2":"","mdepart3":"","address1":"滋賀県守山市大林町214-5","address2":"","tel":"077-581-3636","url":null,"firstvisit":true,"rediagnosis":true,"covid19":"-","doctors":"廣谷秀一","otherinfo":"-"},{"id":"9bacab1b46414c1c6cf1522b800a84e70070854d88e228c59004cff0cd722c2b","name":"ヤザマ内科医院","prefId":"25","mdepart1":"内科小児科","mdepart2":"","mdepart3":"","address1":"滋賀県守山市大門町56-1","address2":"","tel":"077-582-8627","url":"https://www.yazamanaika.com/","firstvisit":false,"rediagnosis":true,"covid19":"-","doctors":"矢間博貴","otherinfo":"-"},{"id":"82e969da1134e0ec346ab23c1877b37ab666e2e9884e236a7952a7f3e39aa55b","name":"うつのみや医院","prefId":"25","mdepart1":"内科小児科","mdepart2":"","mdepart3":"","address1":"滋賀県栗東市十里136-2","address2":"","tel":"077-552-1888","url":"https://shiga-doctor.net","firstvisit":true,"rediagnosis":true,"covid19":"-","doctors":"宇都宮琢史","otherinfo":"-"},{"id":"770760abcd87746953e559758e662ca3ec06a07c19ee330d3967d124c75bbaa7","name":"医療法人社団三愛小児科診療所","prefId":"25","mdepart1":"小児科アレルギー科","mdepart2":"","mdepart3":"","address1":"滋賀県栗東市小柿6丁目10番2号","address2":"","tel":"077-553-6656","url":"http://www.sanaiped.com","firstvisit":true,"rediagnosis":true,"covid19":"-","doctors":"福井徹哉","otherinfo":"-"},{"id":"cc6843f5f7b37934bc6412c10a5e815fd8e17ac3729d8ac1f5af2a8b368e60a9","name":"びわこ皮フ科","prefId":"25","mdepart1":"皮膚科","mdepart2":"","mdepart3":"","address1":"滋賀県栗東市小柿10丁目16-14","address2":"","tel":"077-554-4165","url":"http://biwakohifuka.com/","firstvisit":false,"rediagnosis":true,"covid19":"-","doctors":"田澤隆広","otherinfo":"-"},{"id":"ed1eb25414dda41d65a9eb89b67dc982e234e5090d1fa85536c3500c5e64cc49","name":"パームこどもクリニック","prefId":"25","mdepart1":"小児科アレルギー科心療内科","mdepart2":"","mdepart3":"","address1":"滋賀県栗東市野尻440","address2":"","tel":"077-551-2110","url":"https://www.palmclinic.net","firstvisit":false,"rediagnosis":true,"covid19":"-","doctors":"宇野正章和田志乃","otherinfo":"-"},{"id":"39cb48805d7d9560149a24e357e53ea3b1474ca2eadb68281bb1d4d1fbdb9f6e","name":"(一財）競馬共助会栗東診療所","prefId":"25","mdepart1":"内科","mdepart2":"","mdepart3":"","address1":"滋賀県栗東市御園１０２８","address2":"","tel":"077-558-0039","url":"https://www.ritto-clinic.com","firstvisit":true,"rediagnosis":true,"covid19":"-","doctors":"勝浦章知ほか","otherinfo":"-"},{"id":"a80f964a9a4752b11fcddfcf0dde16b6c4495b13bd5103c587d24351e4629246","name":"寺井医院","prefId":"25","mdepart1":"内科小児科呼吸器内科","mdepart2":"","mdepart3":"","address1":"滋賀県甲賀市甲南町希望ヶ丘本町6丁目857-81","address2":"","tel":"0748-86-1112","url":null,"firstvisit":true,"rediagnosis":true,"covid19":"-","doctors":"寺井繁勝","otherinfo":"-"},{"id":"596f2bb218fb1987202df39be0cc10e2f2458f1cec5436c11fd02573cc01cbac","name":"みなくち内科・消化器内科","prefId":"25","mdepart1":"内科消化器内科","mdepart2":"","mdepart3":"","address1":"滋賀県甲賀市水口町南林口47-2","address2":"","tel":"0748-63-2100","url":"minakuchinaika.com","firstvisit":false,"rediagnosis":true,"covid19":"-","doctors":"吉村彰伸","otherinfo":"-"},{"id":"ce9b982e20ef908cd70cd5d3ec534b8e7832ecf72aca5bdc61eee8373b432e70","name":"あいさか小児科","prefId":"25","mdepart1":"小児科アレルギー科内科","mdepart2":"","mdepart3":"","address1":"滋賀県蒲生郡日野町松尾二丁目88番7","address2":"","tel":"0748-53-8139","url":"http://www.aisaka-shounika.com","firstvisit":true,"rediagnosis":true,"covid19":"-","doctors":"相坂明","otherinfo":"-"},{"id":"14459a0f76708efce455e9c28e7e160b42d43ac463e4cd1e3df796a23930eeb0","name":"浅田クリニック","prefId":"25","mdepart1":"呼吸器内科内科耳鼻咽喉科","mdepart2":"","mdepart3":"","address1":"滋賀県甲賀市水口町東名坂226-1","address2":"","tel":"0748-69-7755","url":"asada-clinic.net","firstvisit":true,"rediagnosis":true,"covid19":"-","doctors":"浅田佳邦","otherinfo":"-"},{"id":"f5fc763faf168b05d49908a802b6c5f7424c9f8c1f0b3cb7a5a565ec5b3b883c","name":"やまもと内科外科クリニック","prefId":"25","mdepart1":"内科外科","mdepart2":"","mdepart3":"","address1":"滋賀県甲賀市水口町虫生野中央111","address2":"","tel":"0748-62-9559","url":"http://www.yamamoto-cl.net","firstvisit":false,"rediagnosis":true,"covid19":"-","doctors":"山元俊行山元弘桜","otherinfo":"-"},{"id":"b5449f36d8987ca060f05f8e0a6d300d75cd136902028d991db31c55ac9bc0a5","name":"布留クリニック","prefId":"25","mdepart1":"内科リウマチ科整形外科皮膚科","mdepart2":"","mdepart3":"","address1":"滋賀県甲賀市甲南町寺庄1098","address2":"","tel":"0748-86-3135","url":"http://www.furu-clinic.jp","firstvisit":true,"rediagnosis":true,"covid19":"-","doctors":"布留守敏","otherinfo":"-"},{"id":"3e90aad561c62a9680d93adfd0fe89007ab38b33ebe0f7f5b9bfadd2a1b94ced","name":"佐藤眼科","prefId":"25","mdepart1":"眼科","mdepart2":"","mdepart3":"","address1":"滋賀県甲賀市水口町名坂781-1","address2":"","tel":"0748-63-5234","url":"https://satoganka.jp","firstvisit":false,"rediagnosis":true,"covid19":"-","doctors":"佐藤友哉","otherinfo":"-"},{"id":"178ab1016f7c1d794278662345e6fe281b2d59790efdc85a85cc4be39654f6e0","name":"ハートクリニックこころ","prefId":"25","mdepart1":"内科","mdepart2":"","mdepart3":"","address1":"滋賀県甲賀市甲南町野尻411","address2":"","tel":"0748-86-0011","url":"http://www.kokoro-shiga.org/","firstvisit":false,"rediagnosis":true,"covid19":"-","doctors":"相馬彰","otherinfo":"-"},{"id":"ca0533038acdcd1a9498579c73267a8d1e4261c1f26bb708301c6581e6ba050f","name":"医療法人田代クリニック","prefId":"25","mdepart1":"内科外科整形外科","mdepart2":"","mdepart3":"","address1":"滋賀県甲賀市水口町新城696","address2":"","tel":"0748-63-0530","url":"https://tashiro-cl.com","firstvisit":false,"rediagnosis":true,"covid19":"-","doctors":"田代圭太郎","otherinfo":"-"},{"id":"d9f101cd3edf26b624cbf2d5ad66a861b444a7dddc8a50824998624335c8db5e","name":"医療法人たちいり小児科医院","prefId":"25","mdepart1":"小児科内科","mdepart2":"","mdepart3":"","address1":"滋賀県野洲市久野部198-1","address2":"","tel":"077-588-0141","url":null,"firstvisit":false,"rediagnosis":true,"covid19":"-","doctors":"立入利晴","otherinfo":"-"},{"id":"5249c085101effa407ab776a48d14ff6fdd8a2026b16a33302c754ec596c5d08","name":"うえだこどもクリニック","prefId":"25","mdepart1":"小児科","mdepart2":"","mdepart3":"","address1":"滋賀県野洲市小篠原869-1","address2":"","tel":"077-596-3751","url":"https://ueda-kodomo.jp/","firstvisit":true,"rediagnosis":true,"covid19":"-","doctors":"上田達哉","otherinfo":"-"},{"id":"65c21a7705680ef2e95085665c2555424f0b82e2214efb42f217e4b4d83c4446","name":"医療生協こうせい駅前診療所","prefId":"25","mdepart1":"内科小児科","mdepart2":"","mdepart3":"","address1":"滋賀県湖南市針337-1","address2":"","tel":"0748-71-3222","url":"http://www.shiga-mcoop.jp/kousei/","firstvisit":false,"rediagnosis":true,"covid19":"-","doctors":"佐々木隆史","otherinfo":"-"},{"id":"ff71a4a278118fb78b43740e3785f13efa3bcaf87e468f1746e262ebd20d7c6b","name":"一般財団法人近江愛隣院今津病院","prefId":"25","mdepart1":"内科","mdepart2":"","mdepart3":"","address1":"滋賀県高島市今津町南新保87番地１","address2":"","tel":"0740-22-2238","url":"http://www.oumiairinen.org/","firstvisit":true,"rediagnosis":true,"covid19":"-","doctors":"安藤三男大野慶人佐々木靖之藤野文孝","otherinfo":"-"},{"id":"7ca026ebec13c545085f3ada67d105fe9a9e3efac557363fa5ed5178258bf744","name":"おかだ小児科医院","prefId":"25","mdepart1":"小児科","mdepart2":"","mdepart3":"","address1":"滋賀県高島市今津町名小路1丁目1-6","address2":"","tel":"0740-22-8071","url":"https://www.okadaiin.com","firstvisit":true,"rediagnosis":true,"covid19":"-","doctors":"岡田清春","otherinfo":"-"},{"id":"768ced04d783b88f1671e2243a424f9df891ff021f165334c90c99d280461d10","name":"東近江市永源寺診療所","prefId":"25","mdepart1":"内科小児科","mdepart2":"","mdepart3":"","address1":"滋賀県東近江市山上町１３５２","address2":"","tel":"0748-27-1160","url":"https://eigenji-clinic.jp","firstvisit":true,"rediagnosis":true,"covid19":"-","doctors":"花戸貴司木田直也","otherinfo":"-"},{"id":"f4cb3d0004fd13ccecdc38e82e36d39cde6606a2d7d5b347422a9fe5d35bcd37","name":"おざき内科医院","prefId":"25","mdepart1":"内科消化器科循環器科","mdepart2":"","mdepart3":"","address1":"滋賀県東近江市小脇町2401-8","address2":"","tel":"0748-23-1911","url":null,"firstvisit":true,"rediagnosis":true,"covid19":"-","doctors":"尾芳樹","otherinfo":"-"},{"id":"d062b5123491804b439a848e2053246449cbd2ea4038e0c1efd575a6bae2af60","name":"医療法人社団双秀会小山眼科クリニック","prefId":"25","mdepart1":"眼科","mdepart2":"","mdepart3":"","address1":"滋賀県東近江市八日市浜野町487-1近江鉄道八日市駅駅舎1階","address2":"","tel":"0748-25-0065","url":"http://www.k-eye.cc","firstvisit":true,"rediagnosis":true,"covid19":"-","doctors":"小山公男","otherinfo":"-"},{"id":"c53f6b2d47bd3a6ba3ee7fcb151dc69e4e0efedf31db0e9de4e698d3840151df","name":"島田医院","prefId":"25","mdepart1":"内科","mdepart2":"","mdepart3":"","address1":"滋賀県東近江市八日市金屋2丁目1番7号","address2":"","tel":"0748-22-0140","url":null,"firstvisit":true,"rediagnosis":true,"covid19":"-","doctors":"島田徹","otherinfo":"-"},{"id":"7f9741b81ff65e92e17ecb85d0d2a6b688a9f4173448e8f99f298c51465bff81","name":"医療法人社団朝日医院","prefId":"25","mdepart1":"内科小児科","mdepart2":"","mdepart3":"","address1":"滋賀県蒲生郡日野町大窪１０１０−１","address2":"","tel":"0748-52-0057","url":"http://www.shigaken-asahi-iin.jp","firstvisit":false,"rediagnosis":true,"covid19":"-","doctors":"朝日新","otherinfo":"-"}]
