[{"name":"トメモリ眼科・形成外科","mdepart1":"眼科","mdepart2":"形成外科","mdepart3":null,"address1":"和歌山県橋本市","address2":"市脇5-4-23","tel":"0736329358","url":"http://www.tomemori-ganka.com/","rediagnosis":true,"covid19":false,"otherinfo":"https://clinics.medley.life/clinics/59a50af69441f10088ac0423"},{"name":"医療法人 ふくはらこどもクリニック","mdepart1":"小児科","mdepart2":"アレルギー科","mdepart3":null,"address1":"和歌山県田辺市","address2":"朝日ヶ丘13‐24‐１F","tel":"0739337711","url":"http://www.fukuhara-kodomo.com/","rediagnosis":true,"covid19":false,"otherinfo":"https://clinics.medley.life/clinics/580964fdaf3fd70008fd207e"},{"name":"野田医院","mdepart1":"内科","mdepart2":"循環器内科","mdepart3":null,"address1":"和歌山県有田郡有田川町","address2":"庄574","tel":null,"url":"http://ncl.jp","rediagnosis":true,"covid19":false,"otherinfo":null},{"name":"森女性クリニック","mdepart1":"産婦人科","mdepart2":"産科","mdepart3":"婦人科","address1":"和歌山県和歌山市","address2":"太田1-10-13","tel":"0734887027","url":"http://www.mori-ladies.com","rediagnosis":true,"covid19":false,"otherinfo":"https://clinics.medley.life/clinics/5dba71f7658c0e66690d4e6b"},{"name":"医療法人 たいようファミリークリニック","mdepart1":"小児科","mdepart2":null,"mdepart3":null,"address1":"和歌山県和歌山市","address2":"新中島125-1","tel":"0734765171","url":"http://taiyo-kodomo.com/index.php","rediagnosis":true,"covid19":false,"otherinfo":"https://clinics.medley.life/clinics/5e571a94dcc9e7285550fd09"},{"name":"おくむらクリニック","mdepart1":"精神科","mdepart2":"老年内科","mdepart3":null,"address1":"和歌山県和歌山市","address2":"十二番丁９ リヴァージュ十二番丁ビル2F","tel":null,"url":"https://okumura-mental.com/","rediagnosis":false,"covid19":false,"otherinfo":null}]
